telebom/__init__.py
telebom/telebom.py
telebom-6.1.8.dist-info/METADATA
telebom-6.1.8.dist-info/WHEEL
telebom-6.1.8.dist-info/top_level.txt
telebom-6.1.8.dist-info/RECORD
